MISO/__init__.py
MISO/test.py
MISO/misopy/Gene.py
MISO/misopy/__init__.py
MISO/misopy/as_events.py
MISO/misopy/cluster_utils.py
MISO/misopy/compare_miso.py
MISO/misopy/credible_intervals.py
MISO/misopy/exon_utils.py
MISO/misopy/filter_events.py
MISO/misopy/gff_utils.py
MISO/misopy/hypothesis_test.py
MISO/misopy/index_gff.py
MISO/misopy/json_utils.py
MISO/misopy/kde_subclass.py
MISO/misopy/legacy_test_pysplicing.py
MISO/misopy/misc_utils.py
MISO/misopy/miso.py
MISO/misopy/miso_db.py
MISO/misopy/miso_pack.py
MISO/misopy/miso_sampler.py
MISO/misopy/miso_utils.py
MISO/misopy/miso_zip.py
MISO/misopy/module_availability.py
MISO/misopy/parse_csv.py
MISO/misopy/parse_gene.py
MISO/misopy/pe_utils.py
MISO/misopy/pickle_utils.py
MISO/misopy/py2c_gene.py
MISO/misopy/read_simulator.py
MISO/misopy/reads_utils.py
MISO/misopy/run_events_analysis.py
MISO/misopy/run_miso.py
MISO/misopy/sam_rpkm.py
MISO/misopy/sam_to_bam.py
MISO/misopy/sam_utils.py
MISO/misopy/samples_utils.py
MISO/misopy/settings.py
MISO/misopy/summarize_miso.py
MISO/misopy/test_cluster.py
MISO/misopy/test_miso.py
MISO/misopy/sashimi_plot/Sashimi.py
MISO/misopy/sashimi_plot/__init__.py
MISO/misopy/sashimi_plot/plot.py
MISO/misopy/sashimi_plot/sashimi_plot.py
MISO/misopy/sashimi_plot/plot_utils/__init__.py
MISO/misopy/sashimi_plot/plot_utils/plot_gene.py
MISO/misopy/sashimi_plot/plot_utils/plot_settings.py
MISO/misopy/sashimi_plot/plot_utils/plotting.py
MISO/misopy/sashimi_plot/plot_utils/samples_plotter.py
rmats2sashimiplot/__init__.py
rmats2sashimiplot/rmats2sashimiplot.py
rmats2sashimiplot-3.0.0.dist-info/LICENSE
rmats2sashimiplot-3.0.0.dist-info/METADATA
rmats2sashimiplot-3.0.0.dist-info/WHEEL
rmats2sashimiplot-3.0.0.dist-info/entry_points.txt
rmats2sashimiplot-3.0.0.dist-info/top_level.txt
rmats2sashimiplot-3.0.0.dist-info/RECORD
