Metadata-Version: 2.1
Name: rmats2sashimiplot
Version: 3.0.0
Summary: rmats2sashimiplot
Home-page: https://github.com/Xinglab/rmats2sashimiplot
Author: Yu-Ting Tseng, Emad Bahrami-Samani, Zhijie Xie, Yukai Jiang
Author-email: shiehshiehzhijie@gmail.com
License: GNU GPLv2
Download-URL: https://github.com/Xinglab/rmats2sashimiplot
Platform: UNKNOWN
Classifier: Programming Language :: Python :: 2
Classifier: Programming Language :: Python :: 3
Classifier: License :: OSI Approved :: GNU General Public License v2 (GPLv2)
